dextract/__init__.py
dextract-0.1.dev7.dist-info/LICENSE
dextract-0.1.dev7.dist-info/METADATA
dextract-0.1.dev7.dist-info/WHEEL
dextract-0.1.dev7.dist-info/top_level.txt
dextract-0.1.dev7.dist-info/RECORD
