Metadata-Version: 2.1
Name: dextract
Version: 0.1.dev7
Summary: Layered extractor of data
Home-page: http://github.com/csehdz/dextract
Author: cseHdz
Author-email: carlos.hdz@me.com
License: MIT
Platform: UNKNOWN
Classifier: Programming Language :: Python :: 3
Classifier: Operating System :: OS Independent
Requires-Python: >=3
Requires-Dist: pandas (>=0.9.1)
Requires-Dist: numpy (>=1.15.4)
Requires-Dist: xlrd (>=1.2.0)
Requires-Dist: pyexcel (>=0.5.10)
Requires-Dist: pyexcel-xls (>=0.5.8)
Requires-Dist: pyexcel-xlsx (>=0.5.7)
Requires-Dist: statistics (>=1.0.3.5)
